batchcompute_cli/__init__.py
batchcompute_cli/cli.py
batchcompute_cli/cli_oss.py
batchcompute_cli/cli_project.py
batchcompute_cli/const.py
batchcompute_cli/i18n_util.py
batchcompute_cli/repl.py
batchcompute_cli/action/__init__.py
batchcompute_cli/action/checker.py
batchcompute_cli/action/cluster.py
batchcompute_cli/action/cluster_create.py
batchcompute_cli/action/cluster_delete.py
batchcompute_cli/action/cluster_update.py
batchcompute_cli/action/config.py
batchcompute_cli/action/disk_type.py
batchcompute_cli/action/events.py
batchcompute_cli/action/image.py
batchcompute_cli/action/image_create.py
batchcompute_cli/action/image_delete.py
batchcompute_cli/action/info.py
batchcompute_cli/action/instance_type.py
batchcompute_cli/action/job.py
batchcompute_cli/action/job_create.py
batchcompute_cli/action/job_delete.py
batchcompute_cli/action/job_restart.py
batchcompute_cli/action/job_stop.py
batchcompute_cli/action/job_submit.py
batchcompute_cli/action/job_update.py
batchcompute_cli/action/log_fetch.py
batchcompute_cli/action/login.py
batchcompute_cli/action/oss_cat.py
batchcompute_cli/action/oss_copy.py
batchcompute_cli/action/oss_delete.py
batchcompute_cli/action/oss_download.py
batchcompute_cli/action/oss_login.py
batchcompute_cli/action/oss_ls.py
batchcompute_cli/action/oss_pwd.py
batchcompute_cli/action/oss_upload.py
batchcompute_cli/action/project_build.py
batchcompute_cli/action/project_create.py
batchcompute_cli/action/project_status.py
batchcompute_cli/action/project_submit.py
batchcompute_cli/action/project_task_add.py
batchcompute_cli/action/project_update.py
batchcompute_cli/action/resource_type.py
batchcompute_cli/externals/__init__.py
batchcompute_cli/externals/command.py
batchcompute_cli/externals/ecs.py
batchcompute_cli/i18ns/__init__.py
batchcompute_cli/i18ns/en.py
batchcompute_cli/i18ns/zh_CN.py
batchcompute_cli/lib/__init__.py
batchcompute_cli/lib/oss2/__init__.py
batchcompute_cli/lib/oss2/api.py
batchcompute_cli-1.3.14a5.dist-info/DESCRIPTION.rst
batchcompute_cli-1.3.14a5.dist-info/METADATA
batchcompute_cli-1.3.14a5.dist-info/RECORD
batchcompute_cli-1.3.14a5.dist-info/WHEEL
batchcompute_cli-1.3.14a5.dist-info/entry_points.txt
batchcompute_cli-1.3.14a5.dist-info/metadata.json
batchcompute_cli-1.3.14a5.dist-info/top_level.txt
