Metadata-Version: 2.0
Name: batchcompute-cli
Version: 1.3.14a5
Summary: Alicloud BatchCompute command line interface
Home-page: http://www.aliyun.com/product/batchcompute
Author: guangchun.luo
Author-email: guangchun.luo@alibaba-inc.com
License: MIT License
Keywords: batchcompute-cli,batchcompute,bcs
Platform: any
Requires-Dist: batchcompute (==2.0.8a8)
Requires-Dist: blessings
Requires-Dist: drawille
Requires-Dist: oss2
Requires-Dist: terminal
